nmrdata/__init__.py
nmrdata/loading.py
nmrdata/main.py
nmrdata/validation.py
nmrdata/version.py
nmrdata/data/__init__.py
nmrdata/data/embeddings.pb
nmrdata/data/standards.pb
nmrdata/parse/__init__.py
nmrdata/parse/add_dssp.py
nmrdata/parse/add_weights.py
nmrdata/parse/cascade_tfrecords.py
nmrdata/parse/label_standardize.py
nmrdata/parse/main.py
nmrdata/parse/metabolite_tfrecords.py
nmrdata/parse/prepare_shiftx_records.py
nmrdata/parse/protein_tfrecords.py
nmrdata/parse/shiftml_tfrecords.py
nmrgnn_data-1.1.0.dist-info/LICENSE
nmrgnn_data-1.1.0.dist-info/METADATA
nmrgnn_data-1.1.0.dist-info/WHEEL
nmrgnn_data-1.1.0.dist-info/entry_points.txt
nmrgnn_data-1.1.0.dist-info/top_level.txt
nmrgnn_data-1.1.0.dist-info/zip-safe
nmrgnn_data-1.1.0.dist-info/RECORD
