Metadata-Version: 2.1
Name: nmrgnn-data
Version: 1.1.0
Summary: Chemical shift prediction dataset
Home-page: https://github.com/ur-whitelab/nmrdata
Author: Ziyue Yang, Andrew White
Author-email: andrew.white@rochester.edu
License: MIT
Classifier: Programming Language :: Python :: 3
Classifier: License :: OSI Approved :: MIT License
Classifier: Operating System :: OS Independent
Classifier: Topic :: Scientific/Engineering :: Bio-Informatics
Classifier: Topic :: Scientific/Engineering :: Artificial Intelligence
License-File: LICENSE
Requires-Dist: tensorflow (>=2.7)
Requires-Dist: click
Requires-Dist: numpy
Requires-Dist: MDAnalysis (~=2.0)
Requires-Dist: importlib-resources
Provides-Extra: parse
Requires-Dist: pdbfixer ; extra == 'parse'
Requires-Dist: biopython ; extra == 'parse'
Requires-Dist: gsd ; extra == 'parse'
Requires-Dist: rdkit-pypi ; extra == 'parse'
